suppy/__init__.py
suppy/feasibility/__init__.py
suppy/feasibility/_linear_algorithms.py
suppy/feasibility/_split_algorithms.py
suppy/feasibility/_bands/_ams_algorithms.py
suppy/feasibility/_bands/_arm_algorithms.py
suppy/feasibility/_bands/_art3_algorithms.py
suppy/feasibility/_halfspaces/_ams_algorithms.py
suppy/feasibility/_hyperplanes/_ams_algorithms.py
suppy/perturbations/__init__.py
suppy/perturbations/_base.py
suppy/projections/__init__.py
suppy/projections/_basic_projections.py
suppy/projections/_projection_methods.py
suppy/projections/_projections.py
suppy/projections/_subgradient_projections.py
suppy/superiorization/__init__.py
suppy/superiorization/_split_sup.py
suppy/superiorization/_standard_sup.py
suppy/superiorization/_sup.py
suppy/superiorization/_deprecated/_sup.py
suppy/superiorization/_deprecated/sup.py
suppy/superiorization/_deprecated/sup_new.py
suppy/utils/__init__.py
suppy/utils/_array_helper.py
suppy/utils/_bounds.py
suppy/utils/_calc_dvh.py
suppy/utils/_decorators.py
suppy/utils/_func_wrapper.py
suppy/utils/plot.py
suppy-0.2.1.dist-info/METADATA
suppy-0.2.1.dist-info/WHEEL
suppy-0.2.1.dist-info/licenses/LICENSE
suppy-0.2.1.dist-info/RECORD
